{
  "coordinates": [
    {
      "index": 0,
      "label": "2 号位",
      "timestamp": 1773227131,
      "x": 1345.7659912109375,
      "y": 19.006999969482422,
      "z": 192.63999938964844
    },
    {
      "index": 2,
      "label": "1 号位",
      "timestamp": 1773227509,
      "x": -42.233001708984375,
      "y": 19.003999710083008,
      "z": 192.74600219726563
    }
  ],
  "features": [
    {
      "detail": 14,
      "index": 56,
      "label": "新外景mesh",
      "price": 0,
      "type": 7,
      "x": 1388.0,
      "y": 0.003000000026077032,
      "z": -0.0020000000949949026
    },
    {
      "detail": 14,
      "index": 62,
      "label": "新外景",
      "price": 0,
      "type": 7,
      "x": 0.0,
      "y": 0.0,
      "z": 0.0
    },
    {
      "detail": 36,
      "index": 252,
      "label": "公司车辆",
      "price": 0,
      "type": 5,
      "x": -30.23900032043457,
      "y": -0.3100000023841858,
      "z": 77.7300033569336
    },
    {
      "detail": 14,
      "index": 295,
      "label": "新外景mesh",
      "price": 0,
      "type": 7,
      "x": 0.0,
      "y": 0.0,
      "z": 0.0
    },
    {
      "detail": 14,
      "index": 296,
      "label": "新外景锚点",
      "price": 0,
      "type": 7,
      "x": 20.0,
      "y": 0.5,
      "z": 130.0
    },
    {
      "detail": 14,
      "index": 416,
      "label": "新外景",
      "price": 0,
      "type": 7,
      "x": 1388.0,
      "y": 0.003000000026077032,
      "z": -0.0020000000949949026
    },
    {
      "detail": 14,
      "index": 514,
      "label": "新外景锚点",
      "price": 0,
      "type": 7,
      "x": 1408.0,
      "y": 0.503000020980835,
      "z": 129.9969940185547
    },
    {
      "detail": 36,
      "index": 531,
      "label": "公司车辆",
      "price": 0,
      "type": 5,
      "x": 1357.760009765625,
      "y": -0.3059999942779541,
      "z": 77.72699737548828
    }
  ]
}